MANIFEST.in
README.md
changelog.txt
setup.py
smaths/__init__.py
smaths.egg-info/PKG-INFO
smaths.egg-info/SOURCES.txt
smaths.egg-info/dependency_links.txt
smaths.egg-info/top_level.txt