Metadata-Version: 1.1
Name: smaths
Version: 0.0.4
Summary: Smaths stands for SquareMATH. Algorithm written exclusively in Python and used to simplify square roots
Home-page: https://github.com/ThatScode24/Math/blob/main/smath.py
Author: Mihai Focsa
Author-email: saftuberraschung@gmail.com
License: MIT
Keywords: simplificator
Platform: UNKNOWN
Classifier: Development Status :: 5 - Production/Stable
Classifier: Intended Audience :: Education
Classifier: Operating System :: Microsoft :: Windows :: Windows 10
Classifier: License :: OSI Approved :: MIT License
Classifier: Programming Language :: Python :: 3
